acp.py
acp_gh-1.1.0.dist-info/licenses/LICENSE
acp_gh-1.1.0.dist-info/METADATA
acp_gh-1.1.0.dist-info/WHEEL
acp_gh-1.1.0.dist-info/entry_points.txt
acp_gh-1.1.0.dist-info/top_level.txt
acp_gh-1.1.0.dist-info/RECORD
