Metadata-Version: 2.4
Name: acp-gh
Version: 1.1.0
Summary: Automatic Commit Pusher (acp) - CLI tool to create GitHub PRs from staged changes in a single command
Author-email: Victor Baranov <bar.victor.2002@gmail.com>
License: GPLv2
Project-URL: Homepage, https://github.com/vbvictor/acp
Project-URL: Repository, https://github.com/vbvictor/acp
Project-URL: Issues, https://github.com/vbvictor/acp/issues
Project-URL: Changelog, https://github.com/vbvictor/acp/releases
Keywords: git,github,gh,github-cli,pull-request,pr,cli,automation,developer-tools,productivity
Classifier: Development Status :: 4 - Beta
Classifier: Environment :: Console
Classifier: Intended Audience :: Developers
Classifier: License :: OSI Approved :: GNU General Public License v2 (GPLv2)
Classifier: Operating System :: OS Independent
Classifier: Programming Language :: Python :: 3
Classifier: Programming Language :: Python :: 3.9
Classifier: Programming Language :: Python :: 3.10
Classifier: Programming Language :: Python :: 3.11
Classifier: Programming Language :: Python :: 3.12
Classifier: Programming Language :: Python :: 3.13
Classifier: Topic :: Software Development :: Version Control :: Git
Classifier: Topic :: Utilities
Requires-Python: >=3.9
License-File: LICENSE
Provides-Extra: dev
Requires-Dist: pytest==8.4.2; extra == "dev"
Requires-Dist: pytest-cov==7.0.0; extra == "dev"
Requires-Dist: ruff==0.14.13; extra == "dev"
Requires-Dist: black==25.11.0; extra == "dev"
Requires-Dist: yamllint==1.37.1; extra == "dev"
Requires-Dist: build==1.4.0; extra == "dev"
Requires-Dist: twine==6.2.0; extra == "dev"
Dynamic: license-file
